beetsplug/webimport/WebImporter.py
beetsplug/webimport/__init__.py
beetsplug/webimport/static/beets.css
beetsplug/webimport/static/jquery.js
beetsplug/webimport/static/util.js
beetsplug/webimport/templates/import.html
beets_web_import-0.0.2.dist-info/METADATA
beets_web_import-0.0.2.dist-info/WHEEL
beets_web_import-0.0.2.dist-info/top_level.txt
beets_web_import-0.0.2.dist-info/RECORD
